odoo8_addon_web_copy_confirm-8.0.1.0.0-py2.7-nspkg.pth
odoo8_addon_web_copy_confirm-8.0.1.0.0.dist-info/DESCRIPTION.rst
odoo8_addon_web_copy_confirm-8.0.1.0.0.dist-info/METADATA
odoo8_addon_web_copy_confirm-8.0.1.0.0.dist-info/RECORD
odoo8_addon_web_copy_confirm-8.0.1.0.0.dist-info/WHEEL
odoo8_addon_web_copy_confirm-8.0.1.0.0.dist-info/metadata.json
odoo8_addon_web_copy_confirm-8.0.1.0.0.dist-info/namespace_packages.txt
odoo8_addon_web_copy_confirm-8.0.1.0.0.dist-info/top_level.txt
odoo_addons/web_copy_confirm/README.rst
odoo_addons/web_copy_confirm/__init__.py
odoo_addons/web_copy_confirm/__openerp__.py
odoo_addons/web_copy_confirm/static/src/js/web_copy_confirm.js
odoo_addons/web_copy_confirm/views/assets.xml
